opensloth/__init__.py
opensloth/_debug_dataloader.py
opensloth/patching/__init__.py
opensloth/patching/ddp_patch.py
opensloth-0.2.1.dist-info/METADATA
opensloth-0.2.1.dist-info/WHEEL
opensloth-0.2.1.dist-info/entry_points.txt
opensloth-0.2.1.dist-info/licenses/LICENSE
opensloth-0.2.1.dist-info/RECORD
