Metadata-Version: 2.4
Name: opensloth
Version: 0.2.1
Summary: A high-performance framework for fine-tuning large language models with multi-GPU support
Project-URL: Homepage, https://github.com/anhvth/opensloth
Project-URL: Repository, https://github.com/anhvth/opensloth
Project-URL: Documentation, https://github.com/anhvth/opensloth
Project-URL: Bug Tracker, https://github.com/anhvth/opensloth/issues
Author-email: anhvth <anhvth.226@gmail.com>
License: MIT
License-File: LICENSE
Keywords: deep learning,fine-tuning,llm,machine learning,multi-gpu,transformers
Classifier: Development Status :: 4 - Beta
Classifier: Intended Audience :: Developers
Classifier: Intended Audience :: Science/Research
Classifier: License :: OSI Approved :: MIT License
Classifier: Operating System :: OS Independent
Classifier: Programming Language :: Python :: 3
Classifier: Programming Language :: Python :: 3.12
Classifier: Topic :: Scientific/Engineering :: Artificial Intelligence
Classifier: Topic :: Software Development :: Libraries :: Python Modules
Requires-Python: >=3.12
Requires-Dist: bitsandbytes>=0.47.0
Requires-Dist: datasets>=3.6.0
Requires-Dist: loguru>=0.7.3
Requires-Dist: poetry>=2.2.0
Requires-Dist: speedy-utils>=1.1.17
Requires-Dist: tensorboardx>=2.6.4
Requires-Dist: transformers>=4.55.4
Requires-Dist: trl>=0.22.2
Requires-Dist: unsloth-zoo>=2025.9.8
Requires-Dist: unsloth>=2025.9.6
Requires-Dist: wandb>=0.21.4
